async_metrics/__init__.py
async_metrics/__main__.py
async_metrics/asyncio.py
async_metrics/sys.py
async_metrics/utils.py
async_metrics/cli/__init__.py
async_metrics/ext/__init__.py
async_metrics/ext/aiohttp.py
async_metrics/ext/restrict_access.py
async_metrics/ext/utils.py
async_metrics/ext/flask/__init__.py
async_metrics/ext/flask/flask.py
tests/__init__.py
tests/test_asyncio.py
tests/test_sys.py
tests/ext/__init__.py
tests/ext/test_aiohttp.py
tests/ext/test_utils.py
async_metrics-0.1.0.dist-info/LICENSE
async_metrics-0.1.0.dist-info/METADATA
async_metrics-0.1.0.dist-info/WHEEL
async_metrics-0.1.0.dist-info/top_level.txt
async_metrics-0.1.0.dist-info/RECORD
