Metadata-Version: 2.1
Name: async-metrics
Version: 0.1.0
Summary: simple metrics for your app
Home-page: https://github.com/amenezes/async_metrics
Author: Alexandre Menezes
Author-email: alexandre.fmenezes@gmail.com
License: Apache-2.0
Project-URL: Documentation, https://github.com/amenezes/async_metrics
Project-URL: Code, https://github.com/amenezes/async_metrics
Project-URL: Issue tracker, https://github.com/amenezes/async_metrics/issues
Project-URL: Changes, https://github.com/amenezes/async_metrics/releases
Keywords: ['asyncio','metrics']
Classifier: Development Status :: 5 - Production/Stable
Classifier: Framework :: AsyncIO
Classifier: Framework :: Flask
Classifier: Intended Audience :: Developers
Classifier: License :: OSI Approved :: Apache Software License
Classifier: Operating System :: OS Independent
Classifier: Programming Language :: Python :: 3 :: Only
Classifier: Programming Language :: Python :: 3.8
Classifier: Programming Language :: Python :: 3.9
Classifier: Programming Language :: Python :: 3.10
Classifier: Programming Language :: Python :: 3.11
Classifier: Programming Language :: Python :: Implementation :: CPython
Classifier: Programming Language :: Python :: Implementation :: PyPy
Classifier: Topic :: Software Development :: Libraries
Requires-Python: >=3.8
License-File: LICENSE
Requires-Dist: psutil (>=5.7.3)
Provides-Extra: cli
Requires-Dist: click (>=8.1.3) ; extra == 'cli'
Requires-Dist: rich (>=12.6.0) ; extra == 'cli'
Requires-Dist: requests (>=2.28.2) ; extra == 'cli'
